{"test_metrics": {"Eval_Ent_Precision": 64.07112199378157, "Eval_Ent_Recall": 62.09150325360488, "Eval_Ent_F1": 63.06578151712036, "Eval_Time": 24.43177556991577, "Eval_Examples": 551, "Eval_Examples_Per_Second": 22.55259747386013, "seen_Eval_Ent_Precision": 7.725321940250986, "seen_Eval_Ent_Recall": 74.11764677508651, "seen_Eval_Ent_F1": 13.992226620783507, "seen_Eval_Time": 20.225212812423706, "seen_Eval_Examples": 551, "seen_Eval_Examples_Per_Second": 27.243223846897582, "unseen_Eval_Ent_Precision": 56.34580011484267, "unseen_Eval_Ent_Recall": 60.740251142445146, "unseen_Eval_Ent_F1": 58.46055978567358, "unseen_Eval_Time": 24.39834976196289, "unseen_Eval_Examples": 551, "unseen_Eval_Examples_Per_Second": 22.58349459597513}}